README.rst
setup.cfg
setup.py
pydron/__init__.py
pydron/decorators.py
pydron/picklesupport.py
pydron/test_all.py
pydron/test_picklesupport.py
pydron/utils.py
pydron/whitelist.py
pydron.egg-info/PKG-INFO
pydron.egg-info/SOURCES.txt
pydron.egg-info/dependency_links.txt
pydron.egg-info/requires.txt
pydron.egg-info/top_level.txt
pydron/backend/__init__.py
pydron/backend/test_worker.py
pydron/backend/worker.py
pydron/config/__init__.py
pydron/config/config.py
pydron/config/test_config.py
pydron/dataflow/__init__.py
pydron/dataflow/graph.py
pydron/dataflow/refine.py
pydron/dataflow/tasks.py
pydron/dataflow/test_graph.py
pydron/dataflow/test_refine.py
pydron/dataflow/test_tasks.py
pydron/dataflow/utils.py
pydron/importhook/__init__.py
pydron/importhook/hook.py
pydron/importhook/test_hook.py
pydron/interpreter/__init__.py
pydron/interpreter/blocking.py
pydron/interpreter/graphdecorator.py
pydron/interpreter/runtime.py
pydron/interpreter/scheduler.py
pydron/interpreter/strategies.py
pydron/interpreter/test_graphdecorator.py
pydron/interpreter/test_traverser.py
pydron/interpreter/traverser.py
pydron/translation/__init__.py
pydron/translation/astwriter.py
pydron/translation/builtins.py
pydron/translation/deassert.py
pydron/translation/declass.py
pydron/translation/decomp.py
pydron/translation/decomplexexpr.py
pydron/translation/dedecorator.py
pydron/translation/dedefault.py
pydron/translation/deexec.py
pydron/translation/defor.py
pydron/translation/defree.py
pydron/translation/deglobal.py
pydron/translation/deimport.py
pydron/translation/deinterrupt.py
pydron/translation/delocals.py
pydron/translation/demembers.py
pydron/translation/demultitarget.py
pydron/translation/deprint.py
pydron/translation/deslice.py
pydron/translation/deunbound.py
pydron/translation/dewith.py
pydron/translation/features.py
pydron/translation/naming.py
pydron/translation/saneitizer.py
pydron/translation/scoping.py
pydron/translation/test_deassert.py
pydron/translation/test_declass.py
pydron/translation/test_decomp.py
pydron/translation/test_decomplexexpr.py
pydron/translation/test_dedecorator.py
pydron/translation/test_dedefault.py
