Metadata-Version: 1.0
Name: pydron
Version: 0.1.4
Summary: Semi-automatic Python parallelization.
Home-page: https://github.com/smurn/pydron
Author: Stefan C. Mueller
Author-email: stefan.mueller@fhnw.ch
License: UNKNOWN
Platform: UNKNOWN
